LICENSE
README.md
pyproject.toml
setup.cfg
setup.py
cleanchausie/__init__.py
cleanchausie/consts.py
cleanchausie/errors.py
cleanchausie/interface.py
cleanchausie/py.typed
cleanchausie/schema.py
cleanchausie/schema_definition.py
cleanchausie/utils.py
cleanchausie.egg-info/PKG-INFO
cleanchausie.egg-info/SOURCES.txt
cleanchausie.egg-info/dependency_links.txt
cleanchausie.egg-info/not-zip-safe
cleanchausie.egg-info/requires.txt
cleanchausie.egg-info/top_level.txt
cleanchausie/ext/__init__.py
cleanchausie/ext/attrs.py
cleanchausie/ext/cleancat.py
cleanchausie/ext/pytz.py
cleanchausie/fields/__init__.py
cleanchausie/fields/field.py
cleanchausie/fields/type_map.py
cleanchausie/fields/utils.py
cleanchausie/fields/validation.py
cleanchausie/fields/types/__init__.py
cleanchausie/fields/types/any.py
cleanchausie/fields/types/bools.py
cleanchausie/fields/types/datetimes.py
cleanchausie/fields/types/dicts.py
cleanchausie/fields/types/enums.py
cleanchausie/fields/types/instances.py
cleanchausie/fields/types/lists.py
cleanchausie/fields/types/nested.py
cleanchausie/fields/types/numbers.py
cleanchausie/fields/types/polymorphic.py
cleanchausie/fields/types/strings.py
cleanchausie/fields/types/tuples.py
cleanchausie/fields/types/tzinfo.py
cleanchausie/fields/types/unions.py
cleanchausie/mypy/__init__.py
cleanchausie/mypy/plugin.py