Metadata-Version: 2.1
Name: cleanchausie
Version: 1.17.7
Summary: Data validation and transformation library for Python. Successor to CleanCat.
Home-page: http://github.com/closeio/cleanchausie
Author: Alec Rosenbaum
Author-email: engineering@close.io
Maintainer: Alec Rosenbaum
Maintainer-email: engineering@close.io
License: MIT
Platform: any
Classifier: Environment :: Web Environment
Classifier: Intended Audience :: Developers
Classifier: License :: OSI Approved :: MIT License
Classifier: Operating System :: OS Independent
Classifier: Programming Language :: Python :: 3
Classifier: Topic :: Internet :: WWW/HTTP :: Dynamic Content
Classifier: Topic :: Software Development :: Libraries :: Python Modules
